yuankong/__init__.py
yuankong/rpa/__init__.py
yuankong/utils/__init__.py
yuankong/utils/bucket.py
yuankong/utils/logManager.py
yuankong-0.8.dist-info/LICENSE
yuankong-0.8.dist-info/METADATA
yuankong-0.8.dist-info/WHEEL
yuankong-0.8.dist-info/top_level.txt
yuankong-0.8.dist-info/RECORD
