Metadata-Version: 2.1
Name: yuankong
Version: 0.8
Summary: Basic function of YuankongAI
Home-page: UNKNOWN
Author: ltq_yuankong
Author-email: 1539365976@qq.com
License: UNKNOWN
Platform: UNKNOWN
Classifier: Programming Language :: Python :: 3
Classifier: License :: OSI Approved :: MIT License
Classifier: Operating System :: OS Independent
License-File: LICENSE
